graphql_db/__init__.py
graphql_db/_version.py
graphql_db/context.py
graphql_db/filter.py
graphql_db/mapper.py
graphql_db/mixin.py
graphql_db/order_by.py
graphql_db/orm_base.py
graphql_db/relay_base.py
graphql_db-1.0.2.dist-info/METADATA
graphql_db-1.0.2.dist-info/WHEEL
graphql_db-1.0.2.dist-info/licenses/LICENSE
graphql_db-1.0.2.dist-info/RECORD
