Metadata-Version: 2.4
Name: graphql-db
Version: 1.0.2
Summary: GraphQL Database Mapper - Generate GraphQL APIs from database models (SQLAlchemy, SQLModel, etc.)
Project-URL: Homepage, https://gitlab.com/parob/graphql-db
Project-URL: Repository, https://gitlab.com/parob/graphql-db
Project-URL: Bug Reports, https://gitlab.com/parob/graphql-db/-/issues
Author-email: Robert Parker <rob@parob.com>
License: MIT
License-File: LICENSE
Keywords: Database,GraphQL,GraphQL API,ORM,SQLAlchemy,SQLModel
Classifier: Development Status :: 3 - Alpha
Classifier: Intended Audience :: Developers
Classifier: License :: OSI Approved :: MIT License
Classifier: Operating System :: OS Independent
Classifier: Programming Language :: Python :: 3
Requires-Python: <3.13,>=3.12
Requires-Dist: context-helper>=1.0.1
Requires-Dist: graphql-api>=1.0.2
Requires-Dist: graphql-core>=3.0.0
Requires-Dist: sqlalchemy-utils>=0.40.0
Requires-Dist: sqlalchemy>=2.0.0
Provides-Extra: dev
Requires-Dist: coverage[toml]>=7.0.0; extra == 'dev'
Requires-Dist: mypy>=1.0.0; extra == 'dev'
Requires-Dist: pytest-cov>=4.0.0; extra == 'dev'
Requires-Dist: pytest>=7.0.0; extra == 'dev'
Requires-Dist: ruff>=0.1.0; extra == 'dev'
Requires-Dist: sqlmodel>=0.0.14; extra == 'dev'
